<?xml version="1.0" encoding="utf-8"?>

<odoo>
    <data>

        <record id="view_partner_edi_supplier_form" model="ir.ui.view">
            <field name="name">res_partner_edi_supplier</field>
            <field name="model">res.partner</field>
            <field name="inherit_id" ref="base.view_partner_form"/>
            <field name="arch" type="xml">

                <xpath expr="//form/sheet/notebook/page[@name='sales_purchases']/group[@name='container_row_2']/group[@name='purchase']/field[@name='supplier']" position="after">
                    <field name="is_edi"/>
                    <field name="is_prices_interface"/>
                </xpath>

            </field>
        </record>


    </data>
</odoo>