<?xml version="1.0"?>

<odoo>
    <record id="invoice_supplier_form" model="ir.ui.view">
        <field name="name">invoice.supplier.form.inherit</field>
        <field name="model">account.invoice</field>
        <field name="inherit_id" ref="account.invoice_supplier_form"/>
        <field name="arch" type="xml">
            <field name="partner_id" position="attributes">
                <attribute name="options">{'no_create': True, 'no_quick_create': True, 'no_create_edit': True}</attribute>
            </field>
            <xpath expr="//field[@name='invoice_line_ids']/tree/field[@name='discount']" position="attributes">
                <attribute name="groups">account.group_account_invoice,sale.group_discount_per_so_line</attribute>
            </xpath>
            <xpath expr="//field[@name='invoice_line_ids']/tree/field[@name='price_unit']" position="after">
                <field name="base_price"/>
            </xpath>
            <xpath expr="//header/button[@name='action_invoice_draft']" position="after">
                <button name="button_update_prices" type="object" string="Upd. Prices" class="btn btn-primary"/>
            </xpath>
            <xpath expr="//field[@name='invoice_line_ids']/tree" position="attributes">
                <attribute name="limit">500</attribute>
            </xpath>
        </field>
    </record>

    <record id="action_invoice_refund" model="ir.actions.act_window">
        <field name="name">Vendor Refunds</field>
        <field name="res_model">account.invoice</field>
        <field name="view_type">form</field>
        <field name="view_mode">tree,form,calendar,pivot,graph</field>
        <field eval="False" name="view_id"/>
        <field name="domain">[('type','=','in_refund')]</field>
        <field name="context">{'default_type': 'in_refund', 'type': 'in_refund', 'journal_type': 'purchase'}</field>
        <field name="search_view_id" ref="account.view_account_invoice_filter"/>
    </record>

    <menuitem id="menu_invoice_refund"
        name="Vendor Refunds"
        parent="purchase.menu_purchase_control"
        sequence="15"
        action="action_invoice_refund"/>
    <record id="invoice_form_inherit" model="ir.ui.view">
        <field name="name">invoice.customer.form.inherit</field>
        <field name="model">account.invoice</field>
        <field name="inherit_id" ref="account.invoice_form"/>
        <field name="arch" type="xml">
            <xpath expr="//field[@name='invoice_line_ids']/tree" position="attributes">
                <attribute name="limit">500</attribute>
            </xpath>
        </field>
    </record>
</odoo>
